krxbot/__init__.py
krxbot/__main__.py
krxbot/calendar.py
krxbot/main.py
krxbot/stock.py
krxbot/utils.py
krxbot-0.0.1.dist-info/METADATA
krxbot-0.0.1.dist-info/WHEEL
krxbot-0.0.1.dist-info/top_level.txt
krxbot-0.0.1.dist-info/RECORD
