Metadata-Version: 2.1
Name: krxbot
Version: 0.0.1
Requires-Dist: krxreader
